kopper/__init__.py
kopper/algorithms.py
kopper/crawler.py
kopper/helper.py
kopper/kopper.py
kopper/parser.py
kopper/schedule.py
kopper/station.py
kopper/train.py
kopper/constants/__init__.py
kopper/constants/days.py
kopper/constants/links.py
kopper/constants/parameters.py
kopper/constants/parsing_map.py
kopper/constants/stations.py
kopper/constants/train_type.py
kopper-0.1.1.dist-info/LICENSE
kopper-0.1.1.dist-info/METADATA
kopper-0.1.1.dist-info/WHEEL
kopper-0.1.1.dist-info/top_level.txt
kopper-0.1.1.dist-info/RECORD
