Metadata-Version: 2.1
Name: kopper
Version: 0.1.1
Summary: This is a Korail seat reservation support service.         If you cannot make a reservation, we will tell you how to make a reservation             by adding an intermediate station.
Home-page: https://github.com/smbyeon/Kopper
Author: Seongmok Byeon
Author-email: smbyun0214@gmail.com
License: UNKNOWN
Platform: UNKNOWN
Classifier: Programming Language :: Python :: 3
Classifier: License :: OSI Approved :: MIT License
Classifier: Operating System :: OS Independent
Requires-Dist: requests
Requires-Dist: beautifulsoup4
